aws_cdk/cdk/_jsii/__init__.py
aws_cdk/cdk/_jsii/cdk@0.36.1.jsii.tgz
aws_cdk.cdk-0.36.1.dist-info/METADATA
aws_cdk.cdk-0.36.1.dist-info/WHEEL
aws_cdk.cdk-0.36.1.dist-info/top_level.txt
aws_cdk.cdk-0.36.1.dist-info/RECORD
