Metadata-Version: 2.1
Name: aws-cdk.cdk
Version: 0.36.1
Summary: Deprecated: this module ha been renamed to @aws-cdk/core
Home-page: https://github.com/awslabs/aws-cdk
Author: Amazon Web Services
License: UNKNOWN
Project-URL: Source, https://github.com/awslabs/aws-cdk.git
Platform: UNKNOWN
Requires-Python: >=3.6
Requires-Dist: jsii (~=0.13.2)
Requires-Dist: publication (>=0.0.3)
